{
    "admin@softwarengineering.com": {
        "password": "admin123",
        "nome": "Mario Rossi",
        "azienda": "Softwarengineering",
        "ruolo": "amministratore",
        "telefono": "+39 075 123456",
        "data_registrazione": "2024-01-15",
        "ultimo_accesso": "2025-09-14 16:04:09",
        "attivo": true
    },
    "test@test.com": {
        "password": "test123",
        "nome": "Giulia Verdi",
        "azienda": "Azienda demo 1",
        "ruolo": "utente",
        "telefono": "+39 075 654321",
        "data_registrazione": "2024-03-20",
        "ultimo_accesso": "2025-09-12 18:24:46",
        "attivo": false
    },
    "demo@demo.com": {
        "password": "demo123",
        "nome": "Luca Bianchi",
        "azienda": "Azienda demo 2",
        "ruolo": "utente",
        "telefono": "+39 075 789012",
        "data_registrazione": "2024-08-10",
        "ultimo_accesso": "2025-09-12 18:16:23",
        "attivo": true
    }
}